steamscordbot/__init__.py
steamscordbot/__main__.py
steamscordbot-0.2.2.dist-info/LICENSE
steamscordbot-0.2.2.dist-info/METADATA
steamscordbot-0.2.2.dist-info/WHEEL
steamscordbot-0.2.2.dist-info/top_level.txt
steamscordbot-0.2.2.dist-info/RECORD
