Metadata-Version: 2.1
Name: steamscordbot
Version: 0.2.2
Summary: Discord bot calling Steam Web API on command
Home-page: https://github.com/esabouraud/steamscordbot
Author: Eric Sabouraud
Author-email: esabouraud@users.noreply.github.com
License: License :: OSI Approved :: BSD License
Platform: UNKNOWN
Classifier: Development Status :: 4 - Beta
Classifier: Programming Language :: Python :: 3.8
Classifier: License :: OSI Approved :: BSD License
Classifier: Operating System :: OS Independent
Classifier: Topic :: Communications :: Chat
Classifier: Topic :: Games/Entertainment
Requires-Python: >=3.8
Requires-Dist: steam
Requires-Dist: discord.py
Requires-Dist: requests
